qiskit_qryd_provider/__init__.py
qiskit_qryd_provider/pcp_gate.py
qiskit_qryd_provider/pcz_gate.py
qiskit_qryd_provider/qryd_backend.py
qiskit_qryd_provider/qryd_job.py
qiskit_qryd_provider/qryd_provider.py
qiskit_qryd_provider-1.0.0.dist-info/LICENSE.txt
qiskit_qryd_provider-1.0.0.dist-info/METADATA
qiskit_qryd_provider-1.0.0.dist-info/WHEEL
qiskit_qryd_provider-1.0.0.dist-info/RECORD
