Metadata-Version: 2.1
Name: qiskit-qryd-provider
Version: 1.0.0
Summary: Qiskit provider for accessing the emulator and future Rydberg quantum computer of the QRydDemo consortium
License: Apache-2.0
Author: Sebastian Weber
Requires-Python: >=3.8,<4.0
Classifier: License :: OSI Approved :: Apache Software License
Classifier: Programming Language :: Python :: 3
Classifier: Programming Language :: Python :: 3.8
Classifier: Programming Language :: Python :: 3.9
Classifier: Programming Language :: Python :: 3.10
Classifier: Programming Language :: Python :: 3.11
Classifier: Programming Language :: Python :: 3.12
Requires-Dist: qiskit (>=1.0)
Requires-Dist: requests (>=2.27)
Project-URL: Documentation, https://thequantumlaend.de/docs/
